jupyter_containds/__init__.py
jupyter_containds/_frontend.py
jupyter_containds/_version.py
jupyter_containds/user.py
jupyter_containds/labextension/package.json
jupyter_containds/labextension/static/114.33b97f4cc21d11de304c.js
jupyter_containds/labextension/static/231.4ee6ef2a463bde4c790a.js
jupyter_containds/labextension/static/231.bb58ddaf669278c2e52c.js
jupyter_containds/labextension/static/41b3825f9204d4b7c82ff31e64a3ed8f.png
jupyter_containds/labextension/static/549.bad2822a2936dee4a92d.js
jupyter_containds/labextension/static/568.092ec1059dc5cdf25ab3.js
jupyter_containds/labextension/static/568.86b6a0fa5486e3dd7062.js
jupyter_containds/labextension/static/remoteEntry.ae78ed2ab7cca8151112.js
jupyter_containds/labextension/static/remoteEntry.f8fb8963f4816ca79e38.js
jupyter_containds/labextension/static/style.js
jupyter_containds/nbextension/__init__.py
jupyter_containds/nbextension/static/extension.js
jupyter_containds/nbextension/static/index.js
jupyter_containds/nbextension/static/index.js.map
jupyter_containds/tests/__init__.py
jupyter_containds/tests/conftest.py
jupyter_containds/tests/test_nbextension_path.py
jupyter_containds/tests/test_user.py
jupyter_containds-0.2.2.data/data/etc/jupyter/nbconfig/notebook.d/jupyter_containds.json
jupyter_containds-0.2.2.data/data/share/jupyter/labextensions/@ideonate/jupyter-containds/package.json
jupyter_containds-0.2.2.data/data/share/jupyter/labextensions/@ideonate/jupyter-containds/static/114.33b97f4cc21d11de304c.js
jupyter_containds-0.2.2.data/data/share/jupyter/labextensions/@ideonate/jupyter-containds/static/231.bb58ddaf669278c2e52c.js
jupyter_containds-0.2.2.data/data/share/jupyter/labextensions/@ideonate/jupyter-containds/static/41b3825f9204d4b7c82ff31e64a3ed8f.png
jupyter_containds-0.2.2.data/data/share/jupyter/labextensions/@ideonate/jupyter-containds/static/549.bad2822a2936dee4a92d.js
jupyter_containds-0.2.2.data/data/share/jupyter/labextensions/@ideonate/jupyter-containds/static/568.092ec1059dc5cdf25ab3.js
jupyter_containds-0.2.2.dist-info/LICENSE
jupyter_containds-0.2.2.dist-info/METADATA
jupyter_containds-0.2.2.dist-info/WHEEL
jupyter_containds-0.2.2.dist-info/top_level.txt
jupyter_containds-0.2.2.dist-info/RECORD
